[
  {
    "ContainingType": "Articles.Comments.Api.Controllers.CommentsController",
    "Method": "GetComments",
    "RelativePath": "v1/articles/{articleId}/comments",
    "HttpMethod": "GET",
    "IsController": true,
    "Order": 0,
    "Parameters": [
      {
        "Name": "articleId",
        "Type": "System.Int32",
        "IsRequired": true
      }
    ],
    "ReturnTypes": [
      {
        "Type": "System.Collections.Generic.List\u00601[[Articles.Comments.Api.DataAdapters.Entities.CommentsDto, Articles.Comments.Api, Version=1.0.0.0, Culture=neutral, PublicKeyToken=null]]",
        "MediaTypes": [
          "text/plain",
          "application/json",
          "text/json"
        ],
        "StatusCode": 200
      }
    ]
  },
  {
    "ContainingType": "Articles.Comments.Api.Controllers.CommentsController",
    "Method": "AddComments",
    "RelativePath": "v1/comments",
    "HttpMethod": "POST",
    "IsController": true,
    "Order": 0,
    "Parameters": [
      {
        "Name": "commentsDto",
        "Type": "Articles.Comments.Api.DataAdapters.Entities.CommentsDto",
        "IsRequired": true
      }
    ],
    "ReturnTypes": [
      {
        "Type": "System.Boolean",
        "MediaTypes": [
          "text/plain",
          "application/json",
          "text/json"
        ],
        "StatusCode": 200
      }
    ]
  },
  {
    "ContainingType": "Articles.Comments.Api.Controllers.CommentsController",
    "Method": "GetCommentById",
    "RelativePath": "v1/comments/{commentId}",
    "HttpMethod": "GET",
    "IsController": true,
    "Order": 0,
    "Parameters": [
      {
        "Name": "commentId",
        "Type": "System.Int32",
        "IsRequired": true
      }
    ],
    "ReturnTypes": [
      {
        "Type": "Articles.Comments.Api.DataAdapters.Entities.CommentsDto",
        "MediaTypes": [
          "text/plain",
          "application/json",
          "text/json"
        ],
        "StatusCode": 200
      }
    ]
  },
  {
    "ContainingType": "Articles.Comments.Api.Controllers.CommentsController",
    "Method": "DeleteComment",
    "RelativePath": "v1/comments/{commentId}",
    "HttpMethod": "DELETE",
    "IsController": true,
    "Order": 0,
    "Parameters": [
      {
        "Name": "commentId",
        "Type": "System.Int32",
        "IsRequired": true
      }
    ],
    "ReturnTypes": [
      {
        "Type": "System.Boolean",
        "MediaTypes": [
          "text/plain",
          "application/json",
          "text/json"
        ],
        "StatusCode": 200
      }
    ]
  }
]